{"stats":{"minecraft:custom":{"minecraft:jump":3,"minecraft:time_since_rest":1127,"minecraft:play_one_minute":1127,"minecraft:leave_game":1,"minecraft:walk_on_water_one_cm":112,"minecraft:walk_one_cm":1500,"minecraft:time_since_death":1127,"minecraft:interact_with_crafting_table":1},"minecraft:picked_up":{"minecraftmod:ruby_block":1,"minecraftmod:ruby":1,"minecraftmod:sapphire":1},"minecraft:mined":{"minecraftmod:ruby_block":1,"minecraftmod:sapphire_ore":1,"minecraftmod:ruby_ore":1},"minecraft:used":{"minecraftmod:ruby_block":1},"minecraft:crafted":{"minecraftmod:ruby_block":2,"minecraftmod:ruby":18}},"DataVersion":2586}